<?xml version="1.0" ?>
<openerp>
	<data>
	    <record id="view_partner_form2" model="ir.ui.view">
            <field name="name">res.partner.form</field>
            <field name="model">res.partner</field>
            <field name="inherit_id" ref="base.view_partner_form"/>
            <field name="arch" type="xml">
                <field name="credit_limit" position="before">
                    <field name="credit_overdue"/>
                    <field name="order_amount"/>
                    <field name="order_all"/>
                    <field name="credit_limit_pacarbel"/>                    
                </field>
            </field>
        </record>
	 
	</data>
</openerp>
